soren/__init__.py
soren/cli.py
soren/client.py
soren/config.py
soren/schema.py
soren/validation.py
soren/processors/__init__.py
soren/processors/agent_workflow.py
soren-0.2.1.dist-info/licenses/LICENSE
soren-0.2.1.dist-info/METADATA
soren-0.2.1.dist-info/WHEEL
soren-0.2.1.dist-info/entry_points.txt
soren-0.2.1.dist-info/top_level.txt
soren-0.2.1.dist-info/RECORD
