Metadata-Version: 2.4
Name: soren
Version: 0.2.1
Summary: Soren AI - Command-line interface for AI evaluation framework
Author: Soren Team
License-Expression: MIT
Project-URL: Homepage, https://github.com/soren-ai/soren-fieldguide
Project-URL: Documentation, https://github.com/soren-ai/soren-fieldguide
Project-URL: Repository, https://github.com/soren-ai/soren-fieldguide
Keywords: ai,evaluation,llm,testing,cli
Classifier: Development Status :: 3 - Alpha
Classifier: Intended Audience :: Developers
Classifier: Programming Language :: Python :: 3
Classifier: Programming Language :: Python :: 3.8
Classifier: Programming Language :: Python :: 3.9
Classifier: Programming Language :: Python :: 3.10
Classifier: Programming Language :: Python :: 3.11
Classifier: Programming Language :: Python :: 3.12
Requires-Python: >=3.8
License-File: LICENSE
Requires-Dist: requests>=2.28.0
Requires-Dist: PyYAML>=6.0
Requires-Dist: jsonschema>=4.0.0
Dynamic: license-file
